{
  "supported_locales": ["en", "fr"],
  "strings": {
    "username_exists": {
      "en": "This username is already in use!",
      "fr": "Ce nom d'utilisateur est déjà utilisé!"
    },
    "email_exists": {
      "en": "This e-mail address is already associated with an account!",
      "fr": "FRENCH * E-MAIL EXISTS"
    },
    "register_unknown_err": {
      "en": "There was an error while creating your account. Please try again.",
      "fr": "FRENCH * UNKNOWN USER ERROR"
    },
    "generic_error": {
      "en": "An unknown error occured while processing your request.",
      "fr": "FRENCH * UNKNOWN ERROR"
    },
    "no_string": {
      "en": "<no string>",
      "fr": "<no string>"
    },
    "validation_error": {
      "en": "There was an error while validating your request. Please check all the data you entered is correct.",
      "fr": "FRENCH * VALIDATION ERROR"
    },
    "parameter_required": {
      "en": "The parameter is required but was not specified.",
      "fr": "FRENCH * VALIDATION ERROR"
    }
  }
}
